Workbook
Name BudgetCodes_All: OFFSET('Accounting & Mapping Type'!$I$2,0,0,COUNTA('Accounting & Mapping Type'!$I$2:$I$200),1)
Name BudgetCodes_Neg: OFFSET('Accounting & Mapping Type'!$I$2,COUNTIF('Accounting & Mapping Type'!$I$2:$I$200,"+*"),0,COUNTIF('Accounting & Mapping Type'!$I$2:$I$200,"-*"),1)
Name BudgetCodes_Pos: OFFSET('Accounting & Mapping Type'!$I$2,0,0,COUNTIF('Accounting & Mapping Type'!$I$2:$I$200,"+*"),1)

Sheet Accounting & Mapping Type
A1: Accounting Type | B1: Mapping Table | D1: FCM | E1: BS | I1: Budget Code | J1: Flow Code | K1: +BAL | N1: Co Code | O1: Profit Center | P1: Profit Center Name
A2: +BAL_MODCF | B2: +BAL_MODCF | D2: SB | E2: SH | I2: +CAP_CON | J2: +ACH | K2: +BAL | N2: 1000 | O2: INC00 | P2: OTHER INCOME
A3: 2-Line BTB | B3: CA_BANK | D3: SC | E3: AL | I3: +DIV_IN | J3: +FX | K3: +BAL | N3: 1000 | O3: INV00 | P3: INVESTMENT INCOME
A4: 4-Line BTB | B4: CA_OFFSET | D4: KT | E4: VC | I4: +EFT_IN | J4: +WIRE | K4: +BAL | N4: 1840 | O4: INC03 | P4: OTHER INCOME - CM
A5: External | D5: ST | E5: RS | I5: +FX_IN | J5: +WIRE_FP | K5: +BAL | N5: 1840 | O5: INV03 | P5: INVESTMENT INCOME - CM
A6: Receipts | E6: MW | I6: +NONOP_I | J6: -ACH | K6: +BAL | N6: 2200 | O6: INC01 | P6: OTHER INCOME - INDVB
I7: +OP_DEP | J7: -FX | K7: +BAL | N7: 2200 | O7: INV01 | P7: INVESTMENT INCOME - INDVB
I8: +PLADS_I | J8: -WIRE | K8: +BAL | N8: 2400 | O8: INC01 | P8: OTHER INCOME - INDVB
I9: +REINSUR | J9: -WIRE_FP | K9: +BAL | N9: 2400 | O9: INV01 | P9: INVESTMENT INCOME - INDVB
I10: +SA_IN | K10: +BAL | N10: 2500 | O10: INC02 | P10: OTHER INCOME - GRPVB
I11: +STI_IN | K11: +BAL | N11: 2500 | O11: INV02 | P11: INVESTMENT INCOME - GRPVB
I12: +TAXES | K12: +BAL | N12: 2560 | O12: INC05 | P12: OTHER INCOME - CTPFML
I13: -CAP_CON | K13: +BAL | N13: 2600 | O13: INC03 | P13: OTHER INCOME - CM
I14: -DIV_OUT | K14: +BAL | N14: 2600 | O14: INV03 | P14: INVESTMENT INCOME - CM
I15: -EFT_OUT | K15: +BAL | N15: 2810 | O15: INV06 | P15: INVESTMENT INCOME - D&V
I16: -FX_OUT | K16: +BAL
I17: -NONOP_O | K17: +BAL
I18: -OP_EXP | K18: +BAL
I19: -PLADS_O | K19: +BAL
I20: -REINSUR | K20: +BAL
I21: -SA_OUT | K21: +BAL
I22: -STI_OUT | K22: +BAL
I23: -TAXES | K23: +BAL
K24: +BAL
K25: +BAL
K26: +BAL
K27: +BAL
K28: +BAL
K29: +BAL
K30: +BAL
K31: +BAL
K32: +BAL
K33: +BAL
K34: +BAL
K35: +BAL
... K2107: +BAL

Sheet Requirements
A1: Accounting Type | B1: Number of Rows | C1: +BAL_MODCF | D1: 2-Line BTB CA_BANK | E1: 2-Line BTB CA_OFFSET | F1: 2-Line BTB CA_BANK | G1: 2-Line BTB CA_OFFSET | H1: 4-Line BTB CA_BANK | I1: 4-Line BTB CA_OFFSET | J1: 4-Line BTB CA_BANK | K1: 4-Line BTB CA_OFFSET | L1: External Transfer CA_BANK | M1: External CA_OFFSET | N1: Receipts CA_BANK | O1: Receipts CA_OFFSET
A2: +BAL_MODCF | B2: 1 | C2: +BAL_MODCF | D2: CA_BANK | E2: CA_OFFSET | F2: CA_BANK | G2: CA_OFFSET | H2: CA_BANK | I2: CA_OFFSET | J2: CA_BANK | K2: CA_OFFSET | L2: CA_BANK | M2: CA_OFFSET | N2: CA_BANK | O2: CA_BANK
A3: 2-Line BTB CA_BANK | B3: 2 | C3: PET Code or Description | D3: Bank Statement Cash Flow Direction | E3: Bank Statement Cash Flow Direction | F3: Bank Statement Cash Flow Direction | G3: Bank Statement Cash Flow Direction | H3: Bank Statement Cash Flow Direction | I3: Bank Statement Cash Flow Direction | J3: Bank Statement Cash Flow Direction | K3: Bank Statement Cash Flow Direction | L3: Account Code | M3: Account Code | N3: Account Code | O3: Account Code
A4: 2-Line BTB CA_OFFSET | B4: 2 | C4: Offset Budget Code | D4: Account Code | E4: Account Code | F4: Account Code | G4: Account Code | H4: Account Code | I4: Account Code | J4: Account Code | K4: Account Code | L4: PET Code or Description | M4: PET Code or Description | N4: Flow Code | O4: Flow Code
A5: 4-Line BTB CA_BANK | B5: 2 | C5: Flow Code | D5: PET Code or Description | E5: PET Code or Description | F5: PET Code or Description | G5: PET Code or Description | H5: PET Code or Description | I5: PET Code or Description | J5: PET Code or Description | K5: PET Code or Description | L5: Long Text | M5: Long Text | N5: Budget Code | O5: Budget Code
A6: 4-Line BTB CA_OFFSET | B6: 2 | D6: Description 2 | E6: Long Text | F6: Description 2 | G6: Long Text | H6: Description 2 | I6: Long Text | J6: Description 2 | K6: Long Text | L6: Bank GL account | M6: GL account | N6: Description | O6: Description
A7: 4-Line BTB | B7: 4 | D7: Description 3 | E7: GL account (DNP) | F7: Description 3 | G7: GL account (DNP) | H7: Description 3 | I7: GL account | J7: Description 3 | K7: GL account | M7: Cost center | N7: Description 2 | O7: Description 2
A8: External Transfer CA_BANK | B8: 1 | D8: Long Text | F8: Long Text | H8: Long Text | I8: Cost center | J8: Long Text | K8: Cost center | M8: Profit center | N8: Description 3 | O8: Description 3
A9: External Transfer CA_OFFSET | B9: 1 | D9: Bank GL account | F9: Bank GL account | H9: Budget Code | I9: Profit center | J9: Budget Code | K9: Profit center | M9: Trading partner | N9: Long Text | O9: Long Text
A10: Receipts CA_BANK | B10: 1 | H10: Bank GL account | I10: Trading partner | J10: Bank GL account | K10: Trading partner | N10: Bank GL account | O10: GL account
A11: Receipts CA_OFFSET | B11: 1 | O11: Cost center
O12: Profit center
O13: Trading partner

Sheet FCM Input
C1: Copy and Paste as Values in Cooresponding Row, Column C on 'BS Rule Values' Tab | J1: Add formula | K1: As Needed | M1: DNP for 2-Line BTB Offset | O1: N/A for Bank GL Accounts | R1: As Needed
A2: Entered By | B2: Entered Date | C2: Rule for Banking Services | D2: Accounting Type | E2: Flow Code | F2: PET Budget Code | G2: PET Code or Description | H2: Offset Budget Code | I2: Paying Account Code (Outgoing) | J2: Bank Statement Cash Flow Direction | K2: Receiving Account Code (Incoming) | L2: Paying GL Account (Outgoing) | M2: Receiving GL Account (Incoming) | N2: Long Text | O2: Cost center | P2: Profit center | Q2: Trading partner | R2: Description 2 | S2: Description 3
A3: ST | B3: 46288 | D3: +BAL_MODCF | E3: +BAL | F3: +CAP_CON | I3: 1000JPMUS269 | J3: yes
C4: rule is same on both bank & offset. Only change is accounting | D4: 2-Line BTB | K4: CA_Bank G/L should begin with "12026"
D5: 4-Line BTB | M5: DNP
D6: External | J6: paying=D receiving=C
D7: Receipts | M7: DNP
C8: rule is same on both bank & offset. Only change is accounting | J8: yes | K8: CA_Bank G/L should begin with "12026"
M9: DNP
J10: yes | K10: CA_Bank G/L should begin with "12026"
M11: DNP
J12: paying=D receiving=C; Required for 2 & 4 Line Bank | K12: CA_Bank G/L should begin with "12026"
K14: CA_Bank G/L should begin with "12026"
B18: Move flow code, budget codes (both PET and balance offset) together
B19: Direction on 2 and 4 line, remove for other types
B20: Bal budget code
B22: Receipts flow needs budget code
B24: Receiving bank is a credit
B26: Confirm budget code is included in the formula (needed for offset formulas in Kyriba, most likely bank as well)
B29: Isolate/restrict drop downs
B30: If accounting type is balance, mapping table is balance
B31: If 2, 4, receipts, external only option is bank or offset

Sheet BS Rules & Accounting
A1: Mapping Table in Kyriba Under Mapping rule (Formula Do Not Overwrite) | B1: Formula from 'Treasury Ops Input' Tab Column P Must Be Pasted As Values. NO FORMULAS in This Cell | C1: For +BAL_MODCF Only and Receipts & STO (Formula Do Not Overwrite) | D1: Formula Do Not Overwrite | E1: Required for all Offset and Bank Mapping Tables (Formula Do Not Overwrite) | F1: Required for all Offset and Bank Mapping Tables (Formula Do Not Overwrite) | G1: As Needed (Required for Expense Accounts- GL Accounts Between 5000000000-7999999999) (Formula Do Not Overwrite) | H1: As Needed (Required for Revenue Accounts- GL Accounts Between 4000000000-4999999999) (Formula Do Not Overwrite) | I1: As Needed (Required for Intercompany Accounting) (Formula Do Not Overwrite)
A2: Mapping Table | B2: Input Value | C2: Budget Code | D2: Chart of Accounts | E2: GL Account | F2: Long Text | G2: Cost Center | H2: Profit Center | I2: Trading Partner | J2: Created By | K2: Date Created | L2: Rank
D3: =IF(B3<>"","USA_COA","")
D4: =IF(B4<>"","USA_COA","")
D5: =IF(B5<>"","USA_COA","")
D6: =IF(B6<>"","USA_COA","")
D7: =IF(B7<>"","USA_COA","")
D8: =IF(B8<>"","USA_COA","")
D9: =IF(B9<>"","USA_COA","")
D10: =IF(B10<>"","USA_COA","")
D11: =IF(B11<>"","USA_COA","")
D12: =IF(B12<>"","USA_COA","")
D13: =IF(B13<>"","USA_COA","")
D14: =IF(B14<>"","USA_COA","")
... D1001: =IF(B1001<>"","USA_COA","")

Sheet Formuals
A1: ='FCM Input'!D2 -> Accounting Type | B1: ='FCM Input'!G2 -> PET Code or Description | C1: ='FCM Input'!I2 -> Paying Account Code (Outgoing) | D1: ='FCM Input'!E2 -> Flow Code | E1: ='FCM Input'!J2 -> Bank Statement Cash Flow Direction | F1: ='FCM Input'!F2 -> PET Budget Code | G1: ='FCM Input'!L2 -> Paying GL Account (Outgoing) | H1: ='FCM Input'!N2 -> Long Text | I1: ='FCM Input'!O2 -> Cost center | J1: ='FCM Input'!P2 -> Profit center | K1: ='FCM Input'!Q2 -> Trading partner | L1: ='FCM Input'!R2 -> Description 2 | M1: ='FCM Input'!S2 -> Description 3
A2: =IF('FCM Input'!D3<>"",'FCM Input'!D3,"") -> +BAL_MODCF | D2: =IF(A2="+BAL_MODCF","+BAL","") -> +BAL
A3: =IF('FCM Input'!D4<>"",'FCM Input'!D4,"") -> 2-Line BTB
A4: =IF('FCM Input'!D5<>"",'FCM Input'!D5,"") -> 4-Line BTB
A5: =IF('FCM Input'!D6<>"",'FCM Input'!D6,"") -> External
A6: =IF('FCM Input'!D7<>"",'FCM Input'!D7,"") -> Receipts
A7: =IF('FCM Input'!D8<>"",'FCM Input'!D8,"")
A8: =IF('FCM Input'!D9<>"",'FCM Input'!D9,"")
A9: =IF('FCM Input'!D10<>"",'FCM Input'!D10,"")
A10: =IF('FCM Input'!D11<>"",'FCM Input'!D11,"")
A11: =IF('FCM Input'!D12<>"",'FCM Input'!D12,"")
A12: =IF('FCM Input'!D13<>"",'FCM Input'!D13,"")
A13: =IF('FCM Input'!D14<>"",'FCM Input'!D14,"")
A14: =IF('FCM Input'!D15<>"",'FCM Input'!D15,"")
... A1002: =IF('FCM Input'!D1003<>"",'FCM Input'!D1003,"")
